{
  "substitution_alg": {
    "title": "Алгоритмы расчёта замещающих значений",
    "ignoreFields": [
      "key",
      "id"
    ],
    "translations": {
      "module_version": "Версия модуля",
      "update_date": "Дата обновления",
      "alg_name": "Наименование алгоритма",
      "formula": "Формула алгоритма",
      "description": "Описание"
    }
  },
  "substitution_values": {
    "title": "Данные по расчетам замещающих значений",
    "ignoreFields": [
      "generation_object_id",
      "pipeline_id",
      "statement_id",
      "id",
      "highway_id",
      "substitution_algorithm_id"
    ],
    "translations": {
      "create_date": "Дата создания",
      "update_date": "Дата обновления",
      "date_from": "Дата, с",
      "date_to": "Дата, по",
      "problem_duration": "Время нештатной ситуации",
      "generation_object_full_name": "Объект генерации",
      "pipeline_full_name": "Имя трубопровода",
      "description": "Комментарий",
      "heat": "Тепло",
      "weight": "Масса",
      "volume": "Объем",
      "status": "Статус",
      "highway_full_name": "Магистраль"
    }
  },
  "protocol": {
    "title": "Протоколы",
    "ignoreFields": [
      "generation_object_id",
      "id"
    ],
    "translations": {
      "name": "Наименование протокола",
      "create_time": "Дата создания",
      "generation_object_full_name": "Полное имя объекта генерации",
      "generation_object_address": "Адрес объекта генерации",
      "step_save": "Сутки",
      "date_from": "Дата, с",
      "date_to": "Дата, по",
      "formula": "Формула расчета",
      "generation_object_short_name": "Краткое имя объекта генерации"
    }
  },
  "data_protocol": {
    "title": "Данные по протоколам",
    "ignoreFields": [
      "heat_eon_line",
      "enthalpy_coldwater",
      "weight_eon_supply",
      "weight_eon_receive",
      "enthalpy_eon_supply_midweight",
      "enthalpy_eon_receive_midweight",
      "negative_eon_pipes",
      "loss_percent"
    ],
    "translations": {
      "id": "Идентификатор",
      "protocol_id": "Ссылка на протокол",
      "weight_main_pipes_supply": "Масса сетевой воды маг. (М2)",
      "weight_main_pipes_receive": "Масса сетевой воды маг. (М1)",
      "temp_main_pipes_supply_midweight": "Температура ср/вз маг. (t2)",
      "temp_main_pipes_receive_midweight": "Температура ср/вз маг. (t1)",
      "heat_main_pipes": "Тепловая энергия маг.",
      "heat_feedline": "Тепловая энергия подп.",
      "heat_main_pipes_and_feeds": "Тепловая энергия отпущен.",
      "heat_all_eon_pipes": "Тепловая энергия ХН и СН",
      "heat_all_pipes_supply": "Тепловая энергия выработан.",
      "weight_feed_main": "Масса осн. подпитки",
      "weight_feed_emergency": "Масса авар. подпитки",
      "weight_feed_main_incl_losses": "Масса подпитки т/с",
      "weigh_feed_all_eon": "Масса подпитки ХН и СН",
      "weight_thps_losses": "Масса потерь ТЭЦ",
      "temp_coldwater_avg": "Темп. хол. воды",
      "date": "Дата / время"
    }
  },
  "day_statement": {
    "title": "Ведомости по дням",
    "ignoreFields": [
      "substition_variations",
      "final_footer_row_id",
      "final_report_row_id",
      "generation_object_id",
      "pipeline_id",
      "highway_id",
      "type_pipeline_id",
      "protocol_id",
      "type_highway_id",
      "id"
    ],
    "translations": {
      "name_statement": "Наименование ведомости",
      "create_time": "Дата создания",
      "consumer": "Потребитель",
      "date_from": "Дата, с",
      "date_to": "Дата, по",
      "formula_calculating_heat_energy": "Формула расчета тепловой энергии",
      "generation_object_full_name": "Полное имя объекта генерации",
      "generation_object_short_name": "Краткое имя объекта генерации",
      "generation_object_address": "Адрес объекта генерации",
      "heat_system": "Тепловая система",
      "number_md": "Номер вычислителя",
      "pipeline_name": "Трубопровод/паропровод",
      "highway_name": "Магистраль",
      "step_save": "Сутки",
      "fill_status": "Тип заполняемых данных",
      "manual_fill_type": "Тип ручного заполнения"
    }
  },
  "hour_statement": {
    "title": "Ведомости по часам",
    "ignoreFields": [
      "substition_variations",
      "final_footer_row_id",
      "final_report_row_id",
      "generation_object_id",
      "pipeline_id",
      "highway_id",
      "type_pipeline_id",
      "id",
      "protocol_id",
      "type_highway_id"
    ],
    "translations": {
      "name_statement": "Наименование ведомости",
      "create_time": "Дата создания",
      "consumer": "Потребитель",
      "date_from": "Дата, с",
      "date_to": "Дата, по",
      "formula_calculating_heat_energy": "Формула расчета тепловой энергии",
      "generation_object_full_name": "Полное имя объекта генерации",
      "generation_object_short_name": "Краткое имя объекта генерации",
      "generation_object_address": "Адрес объекта генерации",
      "heat_system": "Тепловая система",
      "number_md": "Номер вычислителя",
      "pipeline_name": "Трубопровод/паропровод",
      "highway_name": "Магистраль",
      "step_save": "Час"
    }
  },
  "history_values_by_day": {
    "title": "Данные по дневным ведомостям",
    "ignoreFields": [
      "time_get_data",
      "time_read_data",
      "time_write_data",
      "metering_device_id",
      "pipeline_id",
      "statement_id",
      "highway_id",
      "id"
    ],
    "translations": {
      "heat_energy_cold_water_all_time": "Тепловая энергия холодной воды, накопительное значение",
      "abnormal_context": "Нештатные ситуации (ошибки)",
      "abnormal_worktime": "Время нешт.сит.",
      "abnormal_worktime_all_time": "Время нештатных ситуаций, накопительное значение",
      "baro_press": "Баром. давл. наруж. воздуха",
      "coldwater_temp": "Темп. хол. воды",
      "date_from": "Дата, с",
      "date_to": "Дата, по",
      "enthalpy_coldwater": "Энтальпия холодной воды",
      "enthalpy_cond_return": "Энтальпия трубопровода возврата конденсата",
      "enthalpy_return": "Энтальпия обратного трубопровода",
      "enthalpy_return_awerage": "Энтальпия средневзвешенная обратных трубопроводов",
      "enthalpy_steam": "Энтальпия трубопровода подачи пара",
      "enthalpy_supply": "Энтальпия подающего трубопровода",
      "heat_cold_water": "Тепловая энергия холодной воды",
      "heat_cond_pipe_return_koef": "Тепловая энергия паровой магистрали с учетом коэффициента",
      "heat_cond_return": "Тепловая энергия трубопровода возврата конденсата",
      "heat_cond_return_koef": "Тепловая энергия трубопровода возврата конденсата с учетом коэффициента",
      "heat_energy_cond_return_all_time": "Тепловая энергия трубопровода возврата конденсата, накопительное значение",
      "heat_energy_feed_all_time": "Тепловая энергия трубопровода подпитки, накопительное значение",
      "heat_energy_pipe_all_time": "Тепловая энергия магистрали, накопительное значение",
      "heat_energy_return_all_time": "Тепловая энергия обратного трубопровода, накопительное значение",
      "heat_energy_steam_all_time": "Тепловая энергия трубопровода подачи пара, накопительное значение",
      "heat_energy_steam_pipe_all_time": "Тепловая энергия паровой магистрали, накопительное значение",
      "heat_energy_supply_all_time": "Тепловая энергия подающего трубопровода, накопительное значение",
      "heat_feed": "Тепловая энергия трубопровода подпитки",
      "heat_hot_steam": "Тепловая энергия горячего пара",
      "heat_pipe": "Тепловая энергия магистрали",
      "heat_return": "Тепловая энергия обратного трубопровода",
      "heat_steam": "Тепловая энергия трубопровода подачи пара",
      "heat_steam_pipe": "Тепловая энергия паровой магистрали",
      "heat_supply": "Тепловая энергия подающего трубопровода",
      "outdoor_temp": "Tемпература наружного воздуха",
      "pipeline_negative": "Подмес теплоносителя магистрали",
      "pipeline_positive": "Небаланс теплоносителя",
      "pipeline_temp_diff": "Разница температур магистрали",
      "press_cond_return": "Давление в трубопроводе возврата конденсата",
      "press_feed": "Давление в трубопроводе подпитки",
      "press_return": "Давление в обратном трубопровода",
      "press_steam": "Давление в трубопроводе подачи пара",
      "press_supply": "Давление в подающем трубопровода",
      "regular_worktime": "Время штатной работы",
      "regular_worktime_all_time": "Время штатной работы, накопительное значение",
      "return_rate": "Коэффициент возврата (от 0 до 1)",
      "temp_cond_return": "Температура теплоносителя трубопровода возврата конденсата",
      "temp_feed": "Температура теплоносителя трубопровода подпитки",
      "temp_return": "Температура теплоносителя обратного трубопровода",
      "temp_steam": "Температура теплоносителя трубопровода подачи пара",
      "temp_supply": "Температура теплоносителя подающего трубопровода",
      "vol_cond_return": "Объём теплоносителя трубопровода возврата конденсата",
      "vol_cond_return_all_time": "Объём теплоносителя трубопровода возврата конденсата, накопительное значение",
      "vol_cond_return_incl_koef": "Объём теплоносителя трубопровода возврата конденсата с учетом коэффициента",
      "vol_feed": "Объём теплоносителя трубопровода подпитки",
      "vol_feed_all_time": "Объём теплоносителя трубопровода подпитки, накопительное значение",
      "vol_return": "Объём теплоносителя обратного трубопровода",
      "vol_return_all_time": "Объём теплоносителя обратного трубопровода, накопительное значение",
      "vol_steam": "Объём теплоносителя трубопровода подачи пара",
      "vol_steam_all_time": "Объём теплоносителя трубопровода подачи пара, накопительное значение",
      "vol_supply": "Объём теплоносителя подающего трубопровода",
      "vol_supply_all_time": "Объём теплоносителя подающего трубопровода, накопительное значение",
      "weight_cond_return": "Масса теплоносителя трубопровода возврата конденсата",
      "weight_cond_return_all_time": "Масса теплоносителя трубопровода возврата конденсата, накопительное значение",
      "weight_cond_return_incl_koef": "Масса теплоносителя трубопровода возврата конденсата с учетом коэффициента",
      "weight_feed": "Масса теплоносителя трубопровода подпитки",
      "weight_feed_all_time": "Масса теплоносителя трубопровода подпитки, накопительное значение",
      "weight_return": "Масса теплоносителя обратного трубопровода",
      "weight_return_all_time": "Масса теплоносителя обратного трубопровода, накопительное значение",
      "weight_steam": "Масса теплоносителя трубопровода подачи пара",
      "weight_steam_all_time": "Масса теплоносителя трубопровода подачи пара, накопительное значение",
      "weight_supply": "Масса теплоносителя подающего трубопровода",
      "weight_supply_all_time": "Масса теплоносителя подающего трубопровода, накопительное значение"
    }
  },
  "history_values_by_hour": {
    "title": "Данные по часовым ведомостям",
    "ignoreFields": [
      "time_get_data",
      "time_read_data",
      "time_write_data",
      "metering_device_id",
      "pipeline_id",
      "statement_id",
      "id",
      "highway_id"
    ],
    "translations": {
      "heat_energy_cold_water_all_time":"Тепловая энергия холодной воды, накопительное значение",
      "abnormal_context": "Нештатные ситуации (ошибки)",
      "abnormal_worktime": "Время нешт.сит.",
      "abnormal_worktime_all_time": "Время нештатных ситуаций, накопительное значение",
      "baro_press": "Баром. давл. наруж. воздуха",
      "coldwater_temp": "Темп. хол. воды",
      "date_from": "Дата, с",
      "date_to": "Дата, по",
      "enthalpy_coldwater": "Энтальпия холодной воды",
      "enthalpy_cond_return": "Энтальпия трубопровода возврата конденсата",
      "enthalpy_return": "Энтальпия обратного трубопровода",
      "enthalpy_return_awerage": "Энтальпия средневзвешенная обратных трубопроводов",
      "enthalpy_steam": "Энтальпия трубопровода подачи пара",
      "enthalpy_supply": "Энтальпия подающего трубопровода",
      "heat_cold_water": "Тепловая энергия холодной воды",
      "heat_cond_pipe_return_koef": "Тепловая энергия паровой магистрали с учетом коэффициента",
      "heat_cond_return": "Тепловая энергия трубопровода возврата конденсата",
      "heat_cond_return_koef": "Тепловая энергия трубопровода возврата конденсата с учетом коэффициента",
      "heat_energy_cond_return_all_time": "Тепловая энергия трубопровода возврата конденсата, накопительное значение",
      "heat_energy_feed_all_time": "Тепловая энергия трубопровода подпитки, накопительное значение",
      "heat_energy_pipe_all_time": "Тепловая энергия магистрали, накопительное значение",
      "heat_energy_return_all_time": "Тепловая энергия обратного трубопровода, накопительное значение",
      "heat_energy_steam_all_time": "Тепловая энергия трубопровода подачи пара, накопительное значение",
      "heat_energy_steam_pipe_all_time": "Тепловая энергия паровой магистрали, накопительное значение",
      "heat_energy_supply_all_time": "Тепловая энергия подающего трубопровода, накопительное значение",
      "heat_feed": "Тепловая энергия трубопровода подпитки",
      "heat_hot_steam": "Тепловая энергия горячего пара",
      "heat_pipe": "Тепловая энергия магистрали",
      "heat_return": "Тепловая энергия обратного трубопровода",
      "heat_steam": "Тепловая энергия трубопровода подачи пара",
      "heat_steam_pipe": "Тепловая энергия паровой магистрали",
      "heat_supply": "Тепловая энергия подающего трубопровода",
      "outdoor_temp": "Tемпература наружного воздуха",
      "pipeline_negative": "Подмес теплоносителя магистрали",
      "pipeline_positive": "Небаланс теплоносителя",
      "pipeline_temp_diff": "Разница температур магистрали",
      "press_cond_return": "Давление в трубопроводе возврата конденсата",
      "press_feed": "Давление в трубопроводе подпитки",
      "press_return": "Давление в обратном трубопровода",
      "press_steam": "Давление в трубопроводе подачи пара",
      "press_supply": "Давление в подающем трубопровода",
      "regular_worktime": "Время штатной работы",
      "regular_worktime_all_time": "Время штатной работы, накопительное значение",
      "return_rate": "Коэффициент возврата (от 0 до 1)",
      "temp_cond_return": "Температура теплоносителя трубопровода возврата конденсата",
      "temp_feed": "Температура теплоносителя трубопровода подпитки",
      "temp_return": "Температура теплоносителя обратного трубопровода",
      "temp_steam": "Температура теплоносителя трубопровода подачи пара",
      "temp_supply": "Температура теплоносителя подающего трубопровода",
      "vol_cond_return": "Объём теплоносителя трубопровода возврата конденсата",
      "vol_cond_return_all_time": "Объём теплоносителя трубопровода возврата конденсата, накопительное значение",
      "vol_cond_return_incl_koef": "Объём теплоносителя трубопровода возврата конденсата с учетом коэффициента",
      "vol_feed": "Объём теплоносителя трубопровода подпитки",
      "vol_feed_all_time": "Объём теплоносителя трубопровода подпитки, накопительное значение",
      "vol_return": "Объём теплоносителя обратного трубопровода",
      "vol_return_all_time": "Объём теплоносителя обратного трубопровода, накопительное значение",
      "vol_steam": "Объём теплоносителя трубопровода подачи пара",
      "vol_steam_all_time": "Объём теплоносителя трубопровода подачи пара, накопительное значение",
      "vol_supply": "Объём теплоносителя подающего трубопровода",
      "vol_supply_all_time": "Объём теплоносителя подающего трубопровода, накопительное значение",
      "weight_cond_return": "Масса теплоносителя трубопровода возврата конденсата",
      "weight_cond_return_all_time": "Масса теплоносителя трубопровода возврата конденсата, накопительное значение",
      "weight_cond_return_incl_koef": "Масса теплоносителя трубопровода возврата конденсата с учетом коэффициента",
      "weight_feed": "Масса теплоносителя трубопровода подпитки",
      "weight_feed_all_time": "Масса теплоносителя трубопровода подпитки, накопительное значение",
      "weight_return": "Масса теплоносителя обратного трубопровода",
      "weight_return_all_time": "Масса теплоносителя обратного трубопровода, накопительное значение",
      "weight_steam": "Масса теплоносителя трубопровода подачи пара",
      "weight_steam_all_time": "Масса теплоносителя трубопровода подачи пара, накопительное значение",
      "weight_supply": "Масса теплоносителя подающего трубопровода",
      "weight_supply_all_time": "Масса теплоносителя подающего трубопровода, накопительное значение"
    }
  },
  "consumer": {
    "title": "Потребители",
    "ignoreFields": [
      "id"
    ],
    "translations": {
      "full_name": "Полное наименование потребителя",
      "short_name": "Краткое наименование потребителя",
      "consumer_group": "Группа потребителя"
    }
  },
  "generation_object": {
    "title": "Объекты генерации",
    "ignoreFields": [
      "parent_generation_object_id",
      "generation_object_type_id",
      "photo",
      "type_scheme_id",
      "photo_id",
      "id"
    ],
    "translations": {
      "tpp_representative_post": "Должность представителя ТЭЦ",
      "tpp_representative_fio": "ФИО представителя ТЭЦ",
      "full_name": "Полное наименование объекта генерации",
      "short_name": "Краткое наименование объекта генерации",
      "address": "Адрес",
      "commissioning_date": "Дата ввода в эксплуатацию",
      "specified_electrical_power": "Установленная электрическая мощность",
      "specified_thermal_power": "Установленная тепловая мощность",
      "main_fuel_id": "Основное топливо",
      "summer_heat_carrier_loss": "Нормированные внутристанционные потери теплоносителя в летний период, т/час",
      "winter_heat_carrier_loss": "Нормированные внутристанционные потери теплоносителя в зимний период, т/час",
      "to_balance_borders_loss": "Потери (годовые) от места установки ПУ до границы балансовой принадлежности, Гкал",
      "to_balance_borders_loss_one_highway": "Потери (годовые) от места установки ПУ до границы балансовой принадлежности одной магистрали, Гкал",
      "to_balance_borders_loss_two_highway": "Потери (годовые) от места установки ПУ до границы балансовой принадлежности двух магистралей, Гкал",
      "to_balance_borders_loss_four_highway": "Потери (годовые) от места установки ПУ до границы балансовой принадлежности четырех магистралей, Гкал",
      "from_balance_borders_loss": "Потери (годовые) от границ балансовой принадлежности, Гкал",
      "thermal_energy_loss": "Потери (годовые) тепловой энергии, пар, Гкал",
      "condensate_return": "Возврат конденсата, коэффициент пересчёта"
    }
  },
  "generation_object_type": {
    "title": "Тип объекта генерации",
    "ignoreFields": [
      "id"
    ],
    "translations": {
      "full_name": "Полное наименование типа объекта генерации",
      "short_name": "Краткое наименование типа объекта генерации"
    }
  },
  "pipeline": {
    "title": "Трубопроводы",
    "ignoreFields": [
      "parent_pipeline_id",
      "generation_object_id",
      "type_pipeline_id",
      "kind_heat_system_id",
      "type_heat_system_id",
      "type_scheme_id",
      "assignment_highway_id",
      "direction_highway_id",
      "measured_medium_id",
      "id",
      "highway_id",
      "heat_carrier"
    ],
    "translations": {
      "heat_system": "Тепловая система",
      "full_name": "Наименование трубопровода",
      "pipeline_calc_heat_formula": "Формула тепловой энергии трубопровода",
      "highway_calc_heat_formula": "Формула тепловой энергии магистрали",
      "g_min": "Расход минимальный",
      "g_max": "Расход максимальный",
      "type_fill_data": "Тип заполняемых данных"
    }
  }
}
